audio_processer/__init__.py
audio_processer/audio_recorder.py
audio_processer/audio_transcriber.py
audio_processer-0.1.0.dist-info/LICENSE
audio_processer-0.1.0.dist-info/METADATA
audio_processer-0.1.0.dist-info/WHEEL
audio_processer-0.1.0.dist-info/RECORD
